metann/__init__.py
metann/dependentmodule.py
metann/meta.py
metann/proto.py
metann/utils/__init__.py
metann/utils/containers.py
metann/utils/numpy.py
MetaNN-0.3.2.dist-info/LICENSE
MetaNN-0.3.2.dist-info/METADATA
MetaNN-0.3.2.dist-info/WHEEL
MetaNN-0.3.2.dist-info/top_level.txt
MetaNN-0.3.2.dist-info/RECORD
