Metadata-Version: 2.1
Name: MetaNN
Version: 0.3.2
Summary: MetaNN provides extensions of PyTorch nn.Module for meta learning
Home-page: https://github.com/yhqjohn/MetaModule
Author: Hanqiao Yu
Author-email: yhqjohn@gmail.com
License: UNKNOWN
Project-URL: Bug Tracker, https://github.com/yhqjohn/MetaModule/issues
Platform: UNKNOWN
Classifier: Programming Language :: Python :: 3
Classifier: License :: OSI Approved :: MIT License
Classifier: Operating System :: OS Independent
Requires-Python: >=3.6
Requires-Dist: torch (>=0.4.1)
